{"cameraMode":{"drawMode":0,"name":"Shaded","section":"Shading Mode"},"sceneLighting":true,"audioPlay":false,"sceneViewState":{"m_AlwaysRefresh":false,"showFog":true,"showSkybox":true,"showFlares":true,"showImageEffects":true,"showParticleSystems":true,"showVisualEffectGraphs":true,"m_FxEnabled":true},"in2DMode":false,"pivot":{"x":-0.21049976348876954,"y":-2.995356321334839,"z":-0.14544296264648438},"rotation":{"x":-0.3328911364078522,"y":-0.6637325286865234,"z":0.43078935146331789,"w":-0.5128982663154602},"size":9.553239822387696,"orthographic":false}